xquery/__init__.py
xquery/main_xquery.py
xquery/lib/__init__.py
xquery/lib/config.py
xquery/lib/utility.py
xquery/lib/db/__init__.py
xquery/lib/db/abstract_db_connection.py
xquery/lib/db/db_connections.py
xquery/lib/query/__init__.py
xquery/lib/query/abstract_query.py
xquery/lib/query/queries.py
xquery-0.0.116.dist-info/LICENSE.txt
xquery-0.0.116.dist-info/METADATA
xquery-0.0.116.dist-info/WHEEL
xquery-0.0.116.dist-info/top_level.txt
xquery-0.0.116.dist-info/RECORD
