Metadata-Version: 2.1
Name: xquery
Version: 0.0.116
Summary: A package to easily run queries at SQL Server and BigQuery.
Home-page: https://github.com/Xehron/xquery.git
Author: Xehron
Author-email: Xehron@gmail.com
License: UNKNOWN
Project-URL: Bug Tracker, https://github.com/Xehron/xquery/issues
Platform: UNKNOWN
Classifier: Programming Language :: Python :: 3
Classifier: License :: OSI Approved :: MIT License
Classifier: Operating System :: OS Independent
Requires-Python: >=3.6
License-File: LICENSE.txt
Requires-Dist: pandas
Requires-Dist: pyodbc
Requires-Dist: dataclasses
Requires-Dist: typing
Requires-Dist: google-cloud-bigquery
